{
  "workload": {
    "name": "A100 GPU Training (x4)",
    "duration_hours": 4.0,
    "power_kw": 10.0,
    "energy_kwh": 40.0,
    "priority": "NORMAL"
  },
  "optimal_schedule": {
    "start_slot": 8,
    "end_slot": 15,
    "start_hours_from_now": 4.0,
    "slot_prices": [
      {
        "slot": 8,
        "price": 11.2
      },
      {
        "slot": 9,
        "price": 11.0
      },
      {
        "slot": 10,
        "price": 11.13
      },
      {
        "slot": 11,
        "price": 11.22
      },
      {
        "slot": 12,
        "price": 10.93
      },
      {
        "slot": 13,
        "price": 10.53
      },
      {
        "slot": 14,
        "price": 10.17
      },
      {
        "slot": 15,
        "price": 10.91
      }
    ]
  },
  "cost_analysis": {
    "predicted_cost_jpy": 435.4,
    "baseline_cost_jpy": 494.0,
    "savings_jpy": 58.5,
    "savings_pct": 11.8,
    "cvar_cost_jpy": 462.6,
    "risk_adjusted_cost_jpy": 443.6
  },
  "recommendation": "Run 'A100 GPU Training (x4)' starting in 4.0 hours to save ¥59 (12%) vs running now."
}