{
  "workload": {
    "name": "A100 GPU Training (x4)",
    "duration_hours": 4.0,
    "power_kw": 10.0,
    "energy_kwh": 40.0,
    "priority": "NORMAL"
  },
  "optimal_schedule": {
    "start_slot": 19,
    "end_slot": 26,
    "start_hours_from_now": 9.5,
    "slot_prices": [
      {
        "slot": 19,
        "price": 8.84
      },
      {
        "slot": 20,
        "price": 9.04
      },
      {
        "slot": 21,
        "price": 8.32
      },
      {
        "slot": 22,
        "price": 8.57
      },
      {
        "slot": 23,
        "price": 8.5
      },
      {
        "slot": 24,
        "price": 8.77
      },
      {
        "slot": 25,
        "price": 9.01
      },
      {
        "slot": 26,
        "price": 8.54
      }
    ]
  },
  "cost_analysis": {
    "predicted_cost_jpy": 348.0,
    "baseline_cost_jpy": 527.2,
    "savings_jpy": 179.2,
    "savings_pct": 34.0,
    "cvar_cost_jpy": 383.3,
    "risk_adjusted_cost_jpy": 358.6
  },
  "recommendation": "Run 'A100 GPU Training (x4)' starting in 9.5 hours to save ¥179 (34%) vs running now."
}